cd_analyzer-0.2.0.dist-info/licenses/LICENSE
cdanalyzer/__init__.py
cdanalyzer/analysis.py
cd_analyzer-0.2.0.dist-info/METADATA
cd_analyzer-0.2.0.dist-info/WHEEL
cd_analyzer-0.2.0.dist-info/top_level.txt
cd_analyzer-0.2.0.dist-info/RECORD
