Metadata-Version: 2.4
Name: cd-analyzer
Version: 0.2.0
Summary: A tool for analyzing and plotting circular dichroism (CD) temperature-dependent data and calculating melting temperature (Tm).
Author-email: Your Name <1311343971@qq.com>
License: MIT License
Project-URL: Homepage, https://github.com/Andachten/cd-analysis-tool
Project-URL: Bug Tracker, https://github.com/Andachten/cd-analysis-tool/issues
Keywords: science,biochemistry,circular dichroism,protein,Tm,fitting
Classifier: Development Status :: 4 - Beta
Classifier: Intended Audience :: Science/Research
Classifier: License :: OSI Approved :: MIT License
Classifier: Programming Language :: Python :: 3
Classifier: Programming Language :: Python :: 3.9
Classifier: Programming Language :: Python :: 3.10
Classifier: Programming Language :: Python :: 3.11
Classifier: Topic :: Scientific/Engineering :: Bio-Informatics
Classifier: Topic :: Scientific/Engineering :: Chemistry
Requires-Python: >=3.9
License-File: LICENSE
Requires-Dist: numpy
Requires-Dist: scipy
Requires-Dist: matplotlib
Requires-Dist: pandas
Dynamic: license-file
